.coveragerc
.mailmap
.testr.conf
AUTHORS
CONTRIBUTING.rst
ChangeLog
HACKING.rst
LICENSE
MANIFEST.in
README.rst
babel.cfg
requirements.txt
setup.cfg
setup.py
test-requirements.txt
tox.ini
doc/source/conf.py
doc/source/contributing.rst
doc/source/index.rst
doc/source/installation.rst
doc/source/readme.rst
doc/source/usage.rst
performa/__init__.py
performa.egg-info/PKG-INFO
performa.egg-info/SOURCES.txt
performa.egg-info/dependency_links.txt
performa.egg-info/entry_points.txt
performa.egg-info/not-zip-safe
performa.egg-info/pbr.json
performa.egg-info/requires.txt
performa.egg-info/top_level.txt
performa/engine/__init__.py
performa/engine/aggregator.py
performa/engine/ansible_runner.py
performa/engine/config.py
performa/engine/main.py
performa/engine/player.py
performa/engine/report.py
performa/engine/storage.py
performa/engine/utils.py
performa/modules/__init__.py
performa/modules/atop.py
performa/modules/omsimulator.py
performa/modules/sysbench_oltp.py
performa/scenarios/db/sysbench.rst
performa/scenarios/db/sysbench.yaml
performa/scenarios/mq/omsimulator.rst
performa/scenarios/mq/omsimulator.yaml
performa/tests/__init__.py
performa/tests/atop_sample.txt
performa/tests/omsimulator_sample.txt
performa/tests/test_atop.py
performa/tests/test_omsimulator.py
performa/tests/test_sysbench.py
performa/tests/test_utils.py